{
  "tasks": [
    {
      "subject": "teste",
      "description": "eee",
      "status": 3,
      "dataOverdue": "",
      "dateOverdue": "2022-01-20",
      "id": 11
    },
    {
      "subject": "teste2",
      "description": "dsd",
      "status": 3,
      "dataOverdue": "",
      "dateOverdue": "2022-01-26",
      "id": 12
    },
    {
      "subject": "dsscsc",
      "description": "",
      "status": 2,
      "dataOverdue": "",
      "dateOverdue": "2022-01-27",
      "id": 13
    },
    {
      "subject": "222",
      "description": "",
      "status": 2,
      "dataOverdue": "",
      "dateOverdue": "2022-02-02",
      "id": 14
    },
    {
      "subject": "111",
      "description": "",
      "status": 2,
      "dataOverdue": "",
      "dateOverdue": "2022-01-26",
      "id": 15
    }
  ],
  "users": [
    {
      "name": "maria",
      "email": "joaoa@mail.com",
      "password": "123456",
      "confirmPassword": "123456",
      "id": 1
    },
    {
      "name": "teste",
      "email": "teste@mail.com",
      "password": "123456",
      "confirmPassword": "123456",
      "id": 2
    }
  ]
}